Metadata-Version: 2.1
Name: housing-library-5495
Version: 0.1
Summary: Sample code for coding practice
Author-email: heam koppisetti <heam.koppisetti@tigeranalutics.com>
Project-URL: Homepage, https://github.com/heamkoppisetti/mle-training
Keywords: housing,data training
Classifier: Programming Language :: Python :: 3
Requires-Python: >=3.11
Requires-Dist: numpy
Requires-Dist: pandas
Requires-Dist: scikit-learn
